MANIFEST.in
setup.cfg
setup.py
versioneer.py
Servant.egg-info/PKG-INFO
Servant.egg-info/SOURCES.txt
Servant.egg-info/dependency_links.txt
Servant.egg-info/requires.txt
Servant.egg-info/top_level.txt
servant/__init__.py
servant/_version.py
servant/configuration.py
servant/connection.py
servant/contexts.py
servant/errors.py
servant/lowerdict.py
servant/requests.py
servant/responses.py
servant/routing.py
servant/staticfiles.py
servant/middleware/__init__.py
servant/middleware/logging_middleware.py
servant/middleware/response.py
servant/middleware/security_headers.py
test/test_asyncio.py