Metadata-Version: 1.0
Name: Servant
Version: 2.0.1
Summary: Python 3 asyncio web server
Home-page: https://gitlab.com/mkleehammer/servant
Author: Michael Kleehammer
Author-email: michael@kleehammer.com
License: UNKNOWN
Platform: UNKNOWN
